ocean_jypkg/__init__.py
ocean_jypkg/basemap.py
ocean_jypkg/function.py
ocean_jypkg/khoaOpenApi.py
ocean_jypkg/khoa/__init__.py
ocean_jypkg-0.4.dist-info/METADATA
ocean_jypkg-0.4.dist-info/WHEEL
ocean_jypkg-0.4.dist-info/top_level.txt
ocean_jypkg-0.4.dist-info/RECORD
