Metadata-Version: 2.1
Name: ocean-jypkg
Version: 0.4
Summary: ocean_jypkg
Home-page: http://k-git.ust21.kr/jyim
Author: yoyt23
Author-email: yoyt12@ust21.co.kr
License: UNKNOWN
Keywords: ocean_jypkg
Platform: UNKNOWN
Classifier: Programming Language :: Python :: 3
Classifier: Programming Language :: Python :: 3.2
Classifier: Programming Language :: Python :: 3.3
Classifier: Programming Language :: Python :: 3.4
Classifier: Programming Language :: Python :: 3.5
Classifier: Programming Language :: Python :: 3.6
Classifier: Programming Language :: Python :: 3.7
Requires-Python: >=3
